{"cameraMode":{"drawMode":2,"name":"Shaded Wireframe","section":"Shading Mode"},"sceneLighting":false,"audioPlay":false,"sceneViewState":{"m_AlwaysRefresh":false,"showFog":true,"showSkybox":false,"showFlares":true,"showImageEffects":true,"showParticleSystems":true,"showVisualEffectGraphs":true,"m_FxEnabled":true},"in2DMode":false,"pivot":{"x":0.003109768033027649,"y":0.0,"z":-0.07043659687042237},"rotation":{"x":-0.06520188599824906,"y":-0.8750301003456116,"z":0.12316222488880158,"w":-0.4636038541793823},"size":1.2541104555130005,"orthographic":false}